number_to_words/__init__.py
number_to_words/solution.py
number_to_words/tests.py
number_to_words-0.1.2.data/scripts/ntw_script
number_to_words-0.1.2.data/scripts/number_to_words_script
number_to_words-0.1.2.dist-info/LICENSE
number_to_words-0.1.2.dist-info/METADATA
number_to_words-0.1.2.dist-info/WHEEL
number_to_words-0.1.2.dist-info/top_level.txt
number_to_words-0.1.2.dist-info/RECORD
