Metadata-Version: 2.1
Name: number-to-words
Version: 0.1.2
Summary: Python converter of numbers in figures to words
Home-page: https://github.com/wndessy/number_to_words
Author: Winnie Ndessy
Author-email: wndessy@gmail.com
License: UNKNOWN
Platform: UNKNOWN
Classifier: Programming Language :: Python :: 3
Classifier: License :: OSI Approved :: MIT License
Classifier: Operating System :: OS Independent
